AUTHORS
LICENSE
MANIFEST.in
README.rst
setup.py
django_urlmiddleware.egg-info/PKG-INFO
django_urlmiddleware.egg-info/SOURCES.txt
django_urlmiddleware.egg-info/dependency_links.txt
django_urlmiddleware.egg-info/not-zip-safe
django_urlmiddleware.egg-info/pbr.json
django_urlmiddleware.egg-info/top_level.txt
urlmiddleware/__init__.py
urlmiddleware/base.py
urlmiddleware/conf.py
urlmiddleware/middleware.py
urlmiddleware/urlresolvers.py
urlmiddleware/util/__init__.py
urlmiddleware/util/collections.py